WuaiPojieLuntanjinghuaJi2018DierBufen/README.md
WuaiPojieLuntanjinghuaJi2018DierBufen/__init__.py
WuaiPojieLuntanjinghuaJi2018DierBufen/__main__.py
WuaiPojieLuntanjinghuaJi2018DierBufen/file.epub
WuaiPojieLuntanjinghuaJi2018DierBufen/index.html
WuaiPojieLuntanjinghuaJi2018DierBufen/css/__init__.py
WuaiPojieLuntanjinghuaJi2018DierBufen/css/annotations.css
WuaiPojieLuntanjinghuaJi2018DierBufen/css/main.css
WuaiPojieLuntanjinghuaJi2018DierBufen/css/normalize.css
WuaiPojieLuntanjinghuaJi2018DierBufen/css/popup.css
WuaiPojieLuntanjinghuaJi2018DierBufen/font/__init__.py
WuaiPojieLuntanjinghuaJi2018DierBufen/font/fontello.eot
WuaiPojieLuntanjinghuaJi2018DierBufen/font/fontello.svg
WuaiPojieLuntanjinghuaJi2018DierBufen/font/fontello.ttf
WuaiPojieLuntanjinghuaJi2018DierBufen/font/fontello.woff
WuaiPojieLuntanjinghuaJi2018DierBufen/img/__init__.py
WuaiPojieLuntanjinghuaJi2018DierBufen/img/annotator-glyph-sprite.png
WuaiPojieLuntanjinghuaJi2018DierBufen/img/annotator-icon-sprite.png
WuaiPojieLuntanjinghuaJi2018DierBufen/img/apple-touch-icon.png
WuaiPojieLuntanjinghuaJi2018DierBufen/img/cancelfullscreen.png
WuaiPojieLuntanjinghuaJi2018DierBufen/img/close.png
WuaiPojieLuntanjinghuaJi2018DierBufen/img/fullscreen.png
WuaiPojieLuntanjinghuaJi2018DierBufen/img/loader.gif
WuaiPojieLuntanjinghuaJi2018DierBufen/img/menu-icon.png
WuaiPojieLuntanjinghuaJi2018DierBufen/img/save.png
WuaiPojieLuntanjinghuaJi2018DierBufen/img/saved.png
WuaiPojieLuntanjinghuaJi2018DierBufen/img/settings-s.png
WuaiPojieLuntanjinghuaJi2018DierBufen/img/settings.png
WuaiPojieLuntanjinghuaJi2018DierBufen/img/star.png
WuaiPojieLuntanjinghuaJi2018DierBufen/js/__init__.py
WuaiPojieLuntanjinghuaJi2018DierBufen/js/epub.js
WuaiPojieLuntanjinghuaJi2018DierBufen/js/epub.min.js
WuaiPojieLuntanjinghuaJi2018DierBufen/js/epub.min.map
WuaiPojieLuntanjinghuaJi2018DierBufen/js/hooks.min.js
WuaiPojieLuntanjinghuaJi2018DierBufen/js/hooks.min.map
WuaiPojieLuntanjinghuaJi2018DierBufen/js/reader.js
wuai_pojie_luntanjinghua_ji_2018_dier_bufen-2024.3.5.0.dist-info/METADATA
wuai_pojie_luntanjinghua_ji_2018_dier_bufen-2024.3.5.0.dist-info/WHEEL
wuai_pojie_luntanjinghua_ji_2018_dier_bufen-2024.3.5.0.dist-info/entry_points.txt
wuai_pojie_luntanjinghua_ji_2018_dier_bufen-2024.3.5.0.dist-info/top_level.txt
wuai_pojie_luntanjinghua_ji_2018_dier_bufen-2024.3.5.0.dist-info/RECORD
